MANIFEST.in
README.txt
setup.py
django_mentions.egg-info/PKG-INFO
django_mentions.egg-info/SOURCES.txt
django_mentions.egg-info/dependency_links.txt
django_mentions.egg-info/top_level.txt
mentions/__init__.py
mentions/forms.py
mentions/helpers.py
mentions/mentions.py
mentions/models.py
mentions/registry.py
mentions/signals.py
mentions/tests.py
mentions/urls.py
mentions/utils.py
mentions/views.py
mentions/static/css/jquery.mentions.css
mentions/static/js/jquery.mentions.coffee
mentions/static/js/jquery.mentions.js
mentions/templatetags/__init__.py
mentions/templatetags/mentions.py