Metadata-Version: 1.0
Name: django-mentions
Version: 0.2
Summary: Facebook-like mentions for Django
Home-page: UNKNOWN
Author: Ivan Virabyan
Author-email: UNKNOWN
License: UNKNOWN
Platform: UNKNOWN
